wealthguru/__init__.py
wealthguru/main.py
wealthguru-0.1.dist-info/LICENCE
wealthguru-0.1.dist-info/METADATA
wealthguru-0.1.dist-info/WHEEL
wealthguru-0.1.dist-info/top_level.txt
wealthguru-0.1.dist-info/RECORD
