Metadata-Version: 2.1
Name: wealthguru
Version: 0.1
Summary: Stock market analysis of BSE stocks
Home-page: https://github.com/ravikiranmnaik01/python_packages/wealthguru
Author: ravikiranmnaik01
Author-email: ravikiranmnaik@gmail.com
Classifier: Programming Language :: Python :: 3
Classifier: License :: OSI Approved :: MIT License
Classifier: Operating System :: OS Independent
Requires-Python: >=3.6
License-File: LICENCE
Requires-Dist: numpy >=1.26.4
Requires-Dist: pandas >=2.1.4
Requires-Dist: requests >=2.31.0
Requires-Dist: yfinance >=0.2.41
